{
  "player_id": 201939,
  "season": "2024-25",
  "player_info": {
    "position": "Guard",
    "height": "6-2",
    "weight": "185",
    "team_id": 1610612744,
    "team_abbreviation": "GSW"
  },
  "player_stats": {
    "gp": 70,
    "min": 32.2,
    "pts": 24.5,
    "fga": 18.0,
    "fgm": 8.1,
    "fg_pct": 0.448,
    "fg3a": 11.2,
    "fg3m": 4.4,
    "fg3_pct": 0.397,
    "fta": 4.3,
    "ftm": 4.0,
    "ft_pct": 0.933,
    "oreb": 0.6,
    "dreb": 3.9,
    "reb": 4.4,
    "ast": 6.0,
    "stl": 1.1,
    "blk": 0.4,
    "tov": 2.9,
    "pf": 1.4,
    "plus_minus": 4.3
  }
}